mixins/.git/COMMIT_EDITMSG
mixins/.git/config
mixins/.git/description
mixins/.git/FETCH_HEAD
mixins/.git/HEAD
mixins/.git/hooks/applypatch-msg.sample
mixins/.git/hooks/commit-msg.sample
mixins/.git/hooks/fsmonitor-watchman.sample
mixins/.git/hooks/post-update.sample
mixins/.git/hooks/pre-applypatch.sample
mixins/.git/hooks/pre-commit.sample
mixins/.git/hooks/pre-merge-commit.sample
mixins/.git/hooks/pre-push.sample
mixins/.git/hooks/pre-rebase.sample
mixins/.git/hooks/pre-receive.sample
mixins/.git/hooks/prepare-commit-msg.sample
mixins/.git/hooks/push-to-checkout.sample
mixins/.git/hooks/update.sample
mixins/.git/index
mixins/.git/info/exclude
mixins/.git/logs/HEAD
mixins/.git/logs/refs/heads/main
mixins/.git/logs/refs/remotes/origin/HEAD
mixins/.git/logs/refs/remotes/origin/main
mixins/.git/objects/1a/2f1e2a43f1439dfc303b88847c9f23334a8033
mixins/.git/objects/1f/0d528d752cca2c3fa168b5ff9c0b26e3ae96a4
mixins/.git/objects/7b/d1ec6817178b2c50d0e7bf6ff37adec495d804
mixins/.git/objects/a5/0d248e5ab7f9315791d4731c93714f366048a0
mixins/.git/objects/c6/3be527e3eaa1aba6836f260de88a5fb634c475
mixins/.git/objects/d4/2e4f4ae1b62fba4edffbb71c2935c222ade7f3
mixins/.git/objects/pack/pack-4480c0e93d729d83cf9de0d671191ee98e93b828.idx
mixins/.git/objects/pack/pack-4480c0e93d729d83cf9de0d671191ee98e93b828.pack
mixins/.git/ORIG_HEAD
mixins/.git/packed-refs
mixins/.git/refs/heads/main
mixins/.git/refs/remotes/origin/HEAD
mixins/.git/refs/remotes/origin/main
mixins/.gitignore
mixins/__init__.py
mixins/admin.py
mixins/apps.py
mixins/LICENSE
mixins/migrations/__init__.py
mixins/mixins.py
mixins/models.py
mixins/README.md
mixins/requirements.txt
mixins/tests.py
mixins/views.py
dj_mixins-0.1.1.dist-info/METADATA
dj_mixins-0.1.1.dist-info/WHEEL
dj_mixins-0.1.1.dist-info/RECORD
